build/lib/build/lib/oelint_parser/__init__.py
build/lib/build/lib/oelint_parser/cls_item.py
build/lib/build/lib/oelint_parser/cls_stash.py
build/lib/build/lib/oelint_parser/constants.py
build/lib/build/lib/oelint_parser/inlinerep.py
build/lib/build/lib/oelint_parser/parser.py
build/lib/build/lib/oelint_parser/rpl_regex.py
build/lib/oelint_parser/__init__.py
build/lib/oelint_parser/cls_item.py
build/lib/oelint_parser/cls_stash.py
build/lib/oelint_parser/constants.py
build/lib/oelint_parser/inlinerep.py
build/lib/oelint_parser/parser.py
build/lib/oelint_parser/rpl_regex.py
oelint_parser/__init__.py
oelint_parser/cls_item.py
oelint_parser/cls_stash.py
oelint_parser/constants.py
oelint_parser/inlinerep.py
oelint_parser/parser.py
oelint_parser/rpl_regex.py
oelint_parser/data/const-default.json
oelint_parser-8.8.1.dist-info/licenses/LICENSE
oelint_parser-8.8.1.dist-info/METADATA
oelint_parser-8.8.1.dist-info/WHEEL
oelint_parser-8.8.1.dist-info/top_level.txt
oelint_parser-8.8.1.dist-info/RECORD
