Metadata-Version: 2.4
Name: oelint-parser
Version: 8.8.1
Summary: Alternative parser for bitbake recipe
Maintainer-email: Konrad Weihmann <kweihmann@outlook.com>
License-Expression: BSD-2-Clause
Project-URL: homepage, https://github.com/priv-kweihmann/oelint-parser
Project-URL: repository, https://github.com/priv-kweihmann/oelint-parser.git
Project-URL: bugtracker, https://github.com/priv-kweihmann/oelint-parser/issues
Classifier: Development Status :: 5 - Production/Stable
Classifier: Environment :: Console
Classifier: Intended Audience :: Developers
Classifier: Natural Language :: English
Classifier: Operating System :: POSIX :: Linux
Classifier: Programming Language :: Python :: 3 :: Only
Classifier: Programming Language :: Python :: 3
Classifier: Programming Language :: Python :: 3.10
Classifier: Programming Language :: Python :: 3.11
Classifier: Programming Language :: Python :: 3.12
Classifier: Programming Language :: Python :: 3.13
Classifier: Programming Language :: Python :: 3.14
Requires-Python: >=3.10
License-File: LICENSE
Requires-Dist: regex==2026.1.15
Requires-Dist: Deprecated~=1.2
Provides-Extra: dev
Requires-Dist: Flake8-pyproject==1.2.4; extra == "dev"
Requires-Dist: bump-my-version==1.2.6; extra == "dev"
Requires-Dist: build==1.4.0; extra == "dev"
Requires-Dist: dlint==0.16.0; extra == "dev"
Requires-Dist: flake8==7.3.0; extra == "dev"
Requires-Dist: flake8-2020==1.8.1; extra == "dev"
Requires-Dist: flake8-broken-line==1.0.0; extra == "dev"
Requires-Dist: flake8-bugbear==25.11.29; extra == "dev"
Requires-Dist: flake8-builtins==3.1.0; extra == "dev"
Requires-Dist: flake8-coding==1.3.2; extra == "dev"
Requires-Dist: flake8-commas==4.0.0; extra == "dev"
Requires-Dist: flake8-comprehensions==3.17.0; extra == "dev"
Requires-Dist: flake8-debugger==4.1.2; extra == "dev"
Requires-Dist: flake8-docstrings==1.7.0; extra == "dev"
Requires-Dist: flake8-eradicate==1.5.0; extra == "dev"
Requires-Dist: flake8-executable==2.1.3; extra == "dev"
Requires-Dist: flake8-fixme==1.1.1; extra == "dev"
Requires-Dist: flake8-isort==7.0.0; extra == "dev"
Requires-Dist: flake8-mutable==1.2.0; extra == "dev"
Requires-Dist: flake8-pep3101==3.0.0; extra == "dev"
Requires-Dist: flake8-print==5.0.0; extra == "dev"
Requires-Dist: flake8-quotes==3.4.0; extra == "dev"
Requires-Dist: flake8-requirements==2.3.0; extra == "dev"
Requires-Dist: flake8-variables-names==0.0.6; extra == "dev"
Requires-Dist: pydoc-markdown==4.8.2; extra == "dev"
Requires-Dist: pytest==9.0.2; extra == "dev"
Requires-Dist: pytest-cov==6.3.0; extra == "dev"
Requires-Dist: pytest-forked==1.6.0; extra == "dev"
Requires-Dist: pytest-icdiff==0.9; extra == "dev"
Requires-Dist: pytest-random-order==1.2.0; extra == "dev"
Requires-Dist: pytest-socket==0.7.0; extra == "dev"
Requires-Dist: pytest-sugar==1.1.1; extra == "dev"
Requires-Dist: pytest-tldr==0.2.6; extra == "dev"
Requires-Dist: twine==6.2.0; extra == "dev"
Requires-Dist: wheel~=0.46; extra == "dev"
Dynamic: license-file
